LICENSE
MANIFEST.in
README.md
VERSION
__init__.py
requirements.txt
setup.py
bin/healpix2wcs
doc/TUTORIAL.md
drizzlib/__init__.py
drizzlib/fitsfuncdrizzlib.py
drizzlib/healpix2wcs.py
drizzlib/utils.py
drizzlib.egg-info/PKG-INFO
drizzlib.egg-info/SOURCES.txt
drizzlib.egg-info/dependency_links.txt
drizzlib.egg-info/requires.txt
drizzlib.egg-info/top_level.txt
drizzlib/c_package/dynamic-arrays-dbl.c
drizzlib/c_package/dynamic-arrays-int.c
drizzlib/c_package/optimized.c
drizzlib/c_package/rosetta-sutherland-hodgeman.c